lambdacloud/__init__.py
lambdacloud/_login.py
lambdacloud/cli.py
lambdacloud/constants.py
lambdacloud/lambda_api.py
lambdacloud-0.0.2.dist-info/METADATA
lambdacloud-0.0.2.dist-info/WHEEL
lambdacloud-0.0.2.dist-info/entry_points.txt
lambdacloud-0.0.2.dist-info/top_level.txt
lambdacloud-0.0.2.dist-info/RECORD
