Metadata-Version: 2.1
Name: lambdacloud
Version: 0.0.2
Summary: A Python client library for Lambda Lab's Cloud
Home-page: https://github.com/nateraw/lambdacloud
Author: Nathan Raw
Author-email: naterawdata@gmail.com
License: Apache
Requires-Dist: requests
Requires-Dist: tqdm (>=4.42.1)
Requires-Dist: fire
Requires-Dist: tabulate
Provides-Extra: dev
Requires-Dist: pytest ; extra == 'dev'
Requires-Dist: pytest-cov ; extra == 'dev'
Requires-Dist: black (==22.3) ; extra == 'dev'
Requires-Dist: flake8 (>=3.8.3) ; extra == 'dev'
Requires-Dist: isort (>=5.5.4) ; extra == 'dev'
Requires-Dist: mypy (==0.982) ; extra == 'dev'
Provides-Extra: quality
Requires-Dist: black (==22.3) ; extra == 'quality'
Requires-Dist: flake8 (>=3.8.3) ; extra == 'quality'
Requires-Dist: isort (>=5.5.4) ; extra == 'quality'
Requires-Dist: mypy (==0.982) ; extra == 'quality'
Provides-Extra: testing
Requires-Dist: pytest ; extra == 'testing'
Requires-Dist: pytest-cov ; extra == 'testing'
